setup.py
client/__init__.py
client/client.py
client/client/__init__.py
client/client/add_contact.py
client/client/client_database.py
client/client/del_contact.py
client/client/main_window.py
client/client/main_window_conv.py
client/client/start_dialog.py
client/client/transport.py
client/log/__init__.py
far_far_client_messenger.egg-info/PKG-INFO
far_far_client_messenger.egg-info/SOURCES.txt
far_far_client_messenger.egg-info/dependency_links.txt
far_far_client_messenger.egg-info/requires.txt
far_far_client_messenger.egg-info/top_level.txt